chrpy/__init__.py
chrpy-0.0.1.dist-info/METADATA
chrpy-0.0.1.dist-info/WHEEL
chrpy-0.0.1.dist-info/top_level.txt
chrpy-0.0.1.dist-info/RECORD
