Metadata-Version: 2.1
Name: chrpy
Version: 0.0.1
Summary: x
Author: x
